flask_session/__init__.py
flask_session/sessions.py
flask_session_mongodb-0.5.1.dist-info/LICENSE.rst
flask_session_mongodb-0.5.1.dist-info/WHEEL
flask_session_mongodb-0.5.1.dist-info/METADATA
flask_session_mongodb-0.5.1.dist-info/RECORD
